{
  "breadcrumbHome": "Ana Sayfa",
  "breadcrumbKvkk": "KVKK",
  "badge": "Yasal",
  "title": "KVKK | Kişisel Verilerin",
  "titleHighlight": "Korunması",
  "desc": "6698 sayılı Kişisel Verilerin Korunması Kanunu kapsamında aydınlatma metni ve politikalarımız.",
  "sectionLabel": "KVKK",
  "sectionTitle": "Kişisel Verilerin Korunması Politikaları",
  "viewDetails": "Detayları Görüntüle",
  "links": [
    {
      "title": "Kişisel Verilerin Korunması",
      "description": "6698 sayılı KVKK kapsamında kişisel verilerin işlenmesine ilişkin aydınlatma metni."
    },
    {
      "title": "KVKK Başvuru Formu",
      "description": "Kişisel verilerinizle ilgili başvuru, düzeltme veya silme talepleriniz için başvuru formu."
    },
    {
      "title": "Güvenlik ve Gizlilik Politikası",
      "description": "Web sitemiz ve hizmetlerimiz kapsamında uygulanan güvenlik ve gizlilik politikası."
    },
    {
      "title": "KVKK İşlenmesi Beyanı",
      "description": "Kişisel verilerin hangi amaçlarla ve nasıl işlendiği hakkında detaylı bilgilendirme."
    }
  ]
}
